{
    "likelihood": "HeterodynedTransientLikelihoodFD",
    "gw_injection": "True",
    "gw_load_existing_injection": "True",
    "gw_SNR_threshold_low": "20",
    "gw_SNR_threshold_high": "50",
    "gw_max_injection_attempts": "20",
    "waveform_approximant": "TaylorF2QM_taper",
    "ifos": "H1,L1,V1",
    "eos_file": "None",
    "center_chirp_mass_prior": "True",
    "chirp_mass_prior_delta": "0.10",
    "fmin": "20.0",
    "fref": "20.0",
    "fmax": "2048.0",
    "duration": "None",
    "post_trigger_duration": "2.0",
    "trigger_time": "1187008882.4",
    "psd_file_H1": "AplusDesign_PSD.txt",
    "psd_file_L1": "AplusDesign_PSD.txt",
    "psd_file_V1": "AdV_psd.txt",
    "psd_file_ET1": "/home/twouters2/psds/ET_D_psd.txt",
    "psd_file_ET2": "/home/twouters2/psds/ET_D_psd.txt",
    "psd_file_ET3": "/home/twouters2/psds/ET_D_psd.txt",
    "psd_file_CE": "/home/twouters2/psds/CE_psd.txt",
    "data_file_H1": "None",
    "data_file_L1": "None",
    "data_file_V1": "None",
    "data_file_ET1": "None",
    "data_file_ET2": "None",
    "data_file_ET3": "None",
    "relative_binning_binsize": "500",
    "relative_binning_ref_params_equal_true_params": "False",
    "relative_binning_ref_params": "{\"M_c\": 1.3023405409630757, \"q\": 0.8749999999999999, \"s1_z\": 0.01, \"s2_z\": 0.01, \"lambda_1\": 232.9613208692348, \"lambda_2\": 520.598134087556, \"C_1\": 2, \"C_2\": 2, \"a_1\": 0, \"a_2\": 0, \"d_L\": 120.0, \"t_c\": -0.05815957557656209, \"phase_c\": 1.1644515460827842, \"iota\": 0.8337374361881844, \"psi\": 0.6902000288427731, \"ra\": 5.446571919019908, \"dec\": 0.93640500992398, \"H1_SNR\": 25.190013514921134, \"L1_SNR\": 17.376326507796215, \"V1_SNR\": 8.314356290252908, \"network_SNR\": 31.711228678635567, \"epoch\": 254.0, \"gmst\": 2.7288901910520846, \"trigger_time\": 1187008882.4, \"duration\": 256.0}",
    "transforms": "None",
    "gw_kwargs": "None",
    "n_chains": "1000",
    "n_local_steps": "500",
    "n_global_steps": "1000",
    "n_training_loops": "50",
    "n_production_loops": "20",
    "n_epochs": "50",
    "mala_step_size": "1e-5",
    "mala_step_size_scale": "None",
    "chain_batch_size": "0",
    "batch_size": "5000",
    "n_max_examples": "5000",
    "rq_spline_hidden_units": "128,128",
    "rq_spline_n_bins": "8",
    "rq_spline_n_layers": "10",
    "learning_rate": "0.001",
    "local_thinning": "50",
    "global_thinning": "100",
    "n_NFproposal_batch_size": "100",
    "history_window": "100",
    "n_temperatures": "0",
    "max_temperature": "10.0",
    "n_tempered_steps": "5",
    "verbose": "False",
    "save_training_chains": "False",
    "use_scheduler": "False",
    "seed": "None",
    "sampling_seed": "1",
    "run_sampler": "True",
    "keys_to_plot": "M_c, q, s1_z, s2_z, lambda_1, lambda_2, f_stop, a_1, a_2, d_L, t_c, phase_c, iota, psi, ra, dec",
    "use_QM": "False",
    "use_f_stop": "True",
    "outdir": "."
}